{"checkpoint": {"xp": 200, "description": "Get to a ckeckpoint", "name": "checkpoint", "title": "KEEP CALM AND SAVE!!"}, "gem apprentice": {"xp": 20, "title": "GOTTA FIND THOSE GEMS", "description": "Get 20 gems", "name": "gem apprentice"}, "first death": {"xp": 10, "description": "First death on game", "name": "first death", "title": "KEEP CALM AND PLAY"}, "ghost death": {"xp": 15, "title": "KEEP CALM AND RUN AWAY", "description": "First death to a ghost", "name": "ghost death"}, "gem master": {"xp": 20, "title": "GOTTA FIND THOSE GEMS", "description": "Get ALL the gems", "name": "gem master"}}